{
    "0": {
        "speaker": "",
        "spans": [
            {
                "html": "style='color:#FfFffF'",
                "text": "The chestnut-haired woman led the child upstairs."
            }
        ],
        "atts": {
            "dialog": [
                {
                    "font": "en-dia",
                    "fontSize": 34
                },
                {
                    "font": {},
                    "fontSize": {}
                }
            ]
        }
    },
    "1": {
        "speaker": "",
        "spans": [
            {
                "html": "style='color:#FfFffF'",
                "text": "It was getting darker and darker, but the lights in the residential building were very limited, and obviously not everyone had the right to get off work now."
            }
        ],
        "atts": {
            "dialog": [
                {
                    "font": "en-dia",
                    "fontSize": 34
                },
                {
                    "font": {},
                    "fontSize": {}
                }
            ]
        }
    },
    "2": {
        "speaker": "Taki Shiina",
        "spans": [
            {
                "html": "style='color:#FfFffF'",
                "text": "(They're really busy.)"
            }
        ],
        "atts": {}
    },
    "3": {
        "speaker": "",
        "spans": [
            {
                "html": "style='color:#FfFffF'",
                "text": "Saying that, the conscientious driver waiting downstairs didn't have too many feelings in her heart, but instead took out her phone decisively."
            }
        ],
        "atts": {
            "dialog": [
                {
                    "font": "en-dia",
                    "fontSize": 34
                },
                {
                    "font": {},
                    "fontSize": {}
                }
            ]
        }
    },
    "4": {
        "speaker": "",
        "spans": [
            {
                "html": "style='color:#FfFffF'",
                "text": "Writing lyrics based on scenery and feeling sad about spring and autumn has never been her strength, and it is a privilege to create lyrics that can move her."
            }
        ],
        "atts": {
            "dialog": [
                {
                    "font": "en-dia",
                    "fontSize": 34
                },
                {
                    "font": {},
                    "fontSize": {}
                }
            ]
        }
    },
    "5": {
        "speaker": "",
        "spans": [
            {
                "html": "style='color:#FfFffF'",
                "text": "The screen lit up, she glanced at the subscribed messages, plugged in her headphones, and skillfully clicked on the link."
            }
        ],
        "atts": {
            "dialog": [
                {
                    "font": "en-dia",
                    "fontSize": 34
                },
                {
                    "font": {},
                    "fontSize": {}
                }
            ]
        }
    },
    "6": {
        "speaker": "",
        "spans": [
            {
                "html": "style='color:#FfFffF'",
                "text": "A moment later, a chestnut-gold figure reappeared downstairs."
            }
        ],
        "atts": {
            "dialog": [
                {
                    "font": "en-dia",
                    "fontSize": 34
                },
                {
                    "font": {},
                    "fontSize": {}
                }
            ]
        }
    },
    "7": {
        "speaker": "Soyo Nagasaki",
        "spans": [
            {
                "html": "style='color:#FfFffF'",
                "text": "Where is the car parked..."
            }
        ],
        "atts": {
            "dialog": [
                {
                    "font": "en-dia",
                    "fontSize": 34
                },
                {
                    "font": {},
                    "fontSize": {}
                }
            ]
        }
    },
    "8": {
        "speaker": "",
        "spans": [
            {
                "html": "style='color:#FfFffF'",
                "text": "The Toyota Century has a low-key color scheme, and is silent in the twilight with the part-time driver. And the white-collar worker's eyesight is not very good."
            }
        ],
        "atts": {
            "dialog": [
                {
                    "font": "en-dia",
                    "fontSize": 34
                },
                {
                    "font": {},
                    "fontSize": {}
                }
            ]
        }
    },
    "9": {
        "speaker": "",
        "spans": [
            {
                "html": "style='color:#FfFffF'",
                "text": "Fortunately, the bright pink is too eye-catching in a space without children. Soyo Nagasaki squinted and looked around, finally capturing the abrupt bright color, and a friend who frowned for 20 hours a day."
            }
        ],
        "atts": {
            "dialog": [
                {
                    "font": "en-dia",
                    "fontSize": 34
                },
                {
                    "font": {},
                    "fontSize": {}
                }
            ]
        }
    },
    "10": {
        "speaker": "Soyo Nagasaki",
        "spans": [
            {
                "html": "style='color:#FfFffF'",
                "text": "..."
            }
        ],
        "atts": {
            "dialog": [
                {
                    "font": "en-dia",
                    "fontSize": 34
                },
                {
                    "font": {},
                    "fontSize": {}
                }
            ]
        }
    },
    "11": {
        "speaker": "Soyo Nagasaki",
        "spans": [
            {
                "html": "style='color:#FfFffF'",
                "text": "What are you looking at, little Taki?"
            }
        ],
        "atts": {
            "dialog": [
                {
                    "font": "en-dia",
                    "fontSize": 34
                },
                {
                    "font": {},
                    "fontSize": {}
                }
            ]
        }
    },
    "12": {
        "speaker": "Taki Shiina",
        "spans": [
            {
                "html": "style='color:#FfFffF'",
                "text": "!!!"
            }
        ],
        "atts": {}
    },
    "13": {
        "speaker": "Taki Shiina",
        "spans": [
            {
                "html": "style='color:#FfFffF'",
                "text": "Ha—uh, nothing."
            }
        ],
        "atts": {}
    },
    "14": {
        "speaker": "",
        "spans": [
            {
                "html": "style='color:#FfFffF'",
                "text": "It was too late to hide. The bright pink was too eye-catching in a space without children."
            }
        ],
        "atts": {
            "dialog": [
                {
                    "font": "en-dia",
                    "fontSize": 34
                },
                {
                    "font": {},
                    "fontSize": {}
                }
            ]
        }
    },
    "15": {
        "speaker": "Taki Shiina",
        "spans": [
            {
                "html": "style='color:#FfFffF'",
                "text": "Why do you always like to appear like this."
            }
        ],
        "atts": {}
    },
    "16": {
        "speaker": "Soyo Nagasaki",
        "spans": [
            {
                "html": "style='color:#FfFffF'",
                "text": "So you were watching Anon's live stream. Why are you so serious? What did she do again?"
            }
        ],
        "atts": {
            "dialog": [
                {
                    "font": "en-dia",
                    "fontSize": 34
                },
                {
                    "font": {},
                    "fontSize": {}
                }
            ]
        }
    },
    "17": {
        "speaker": "Taki Shiina",
        "spans": [
            {
                "html": "style='color:#FfFffF'",
                "text": "(What do you mean what did she do again? Has Soyo seen a compilation of this guy's live broadcast accidents?)"
            }
        ],
        "atts": {}
    },
    "18": {
        "speaker": "",
        "spans": [
            {
                "html": "style='color:#FfFffF'",
                "text": "Despite complaining in her heart, the loyal friend still swiped up the soaring messages one by one and pointed them out to her rarely curious teammate."
            }
        ],
        "atts": {
            "dialog": [
                {
                    "font": "en-dia",
                    "fontSize": 34
                },
                {
                    "font": {},
                    "fontSize": {}
                }
            ]
        }
    },
    "19": {
        "speaker": "",
        "spans": [
            {
                "html": "style='color:#FfFffF'",
                "text": "The drummer's movements were very fast, so fast that it seemed deliberate to make people unable to see what the fleeting messages were. What's more, the observer's eyesight is not outstanding."
            }
        ],
        "atts": {
            "dialog": [
                {
                    "font": "en-dia",
                    "fontSize": 34
                },
                {
                    "font": {},
                    "fontSize": {}
                }
            ]
        }
    },
    "20": {
        "speaker": "",
        "spans": [
            {
                "html": "style='color:#FfFffF'",
                "text": "Even so, understanding certain things does not entirely depend on the eyes. MyGO!!!!!'s bassist still saw quite a few voices urging for a Live."
            }
        ],
        "atts": {
            "dialog": [
                {
                    "font": "en-dia",
                    "fontSize": 34
                },
                {
                    "font": {},
                    "fontSize": {}
                }
            ]
        }
    },
    "21": {
        "speaker": "",
        "spans": [
            {
                "html": "style='color:#FfFffF'",
                "text": "The office worker remembered the plane ticket she had just booked yesterday, flying to Hokkaido next week."
            }
        ],
        "atts": {
            "dialog": [
                {
                    "font": "en-dia",
                    "fontSize": 34
                },
                {
                    "font": {},
                    "fontSize": {}
                }
            ]
        }
    },
    "22": {
        "speaker": "",
        "spans": [
            {
                "html": "style='color:#FfFffF'",
                "text": "In this regard, Taki Shiina is always the most innocent of them."
            }
        ],
        "atts": {
            "dialog": [
                {
                    "font": "en-dia",
                    "fontSize": 34
                },
                {
                    "font": {},
                    "fontSize": {}
                }
            ]
        }
    },
    "23": {
        "speaker": "Soyo Nagasaki",
        "spans": [
            {
                "html": "style='color:#FfFffF'",
                "text": "..."
            }
        ],
        "atts": {
            "dialog": [
                {
                    "font": "en-dia",
                    "fontSize": 34
                },
                {
                    "font": {},
                    "fontSize": {}
                }
            ]
        }
    },
    "24": {
        "speaker": "",
        "spans": [
            {
                "html": "style='color:#FfFffF'",
                "text": "That's not how I remember it. In the past, there were people who mentioned MyGO!!!!! in Anon Chihaya's live stream, but it was rare to have one or two in a stream. After all, their activity frequency is almost comparable to a dormant volcano."
            }
        ],
        "atts": {
            "dialog": [
                {
                    "font": "en-dia",
                    "fontSize": 34
                },
                {
                    "font": {},
                    "fontSize": {}
                }
            ]
        }
    },
    "25": {
        "speaker": "",
        "spans": [
            {
                "html": "style='color:#FfFffF'",
                "text": "But the reason is not difficult to guess. The bassist, who is with the drummer, secretly examines the expression of this rock band's leader. Today, she is not wearing makeup, and she is not as energetic as in the two-person co-frame clip."
            }
        ],
        "atts": {
            "dialog": [
                {
                    "font": "en-dia",
                    "fontSize": 34
                },
                {
                    "font": {},
                    "fontSize": {}
                }
            ]
        }
    },
    "26": {
        "speaker": "",
        "spans": [
            {
                "html": "style='color:#FfFffF'",
                "text": "...Although she may be forced to be energetic. After all, she was pulled over by that guy to do business."
            }
        ],
        "atts": {
            "dialog": [
                {
                    "font": "en-dia",
                    "fontSize": 34
                },
                {
                    "font": {},
                    "fontSize": {}
                }
            ]
        }
    },
    "27": {
        "speaker": "Taki Shiina",
        "spans": [
            {
                "html": "style='color:#FfFffF'",
                "text": "Do you usually watch her live streams?"
            }
        ],
        "atts": {}
    },
    "28": {
        "speaker": "Soyo Nagasaki",
        "spans": [
            {
                "html": "style='color:#FfFffF'",
                "text": "No."
            }
        ],
        "atts": {
            "dialog": [
                {
                    "font": "en-dia",
                    "fontSize": 34
                },
                {
                    "font": {},
                    "fontSize": {}
                }
            ]
        }
    },
    "29": {
        "speaker": "Taki Shiina",
        "spans": [
            {
                "html": "style='color:#FfFffF'",
                "text": "This person's title is \"Idiot Pink Hair\". Anon said in her live stream that she doesn't like to be called that. It's too much, even if they donate money."
            }
        ],
        "atts": {}
    },
    "30": {
        "speaker": "Soyo Nagasaki",
        "spans": [
            {
                "html": "style='color:#FfFffF'",
                "text": "That's really impolite... but Anon probably finds it difficult to say it directly as a streamer, and probably pretends not to see it."
            }
        ],
        "atts": {
            "dialog": [
                {
                    "font": "en-dia",
                    "fontSize": 34
                },
                {
                    "font": {},
                    "fontSize": {}
                }
            ]
        }
    },
    "31": {
        "speaker": "Taki Shiina",
        "spans": [
            {
                "html": "style='color:#FfFffF'",
                "text": "That won't do."
            }
        ],
        "atts": {}
    },
    "32": {
        "speaker": "",
        "spans": [
            {
                "html": "style='color:#FfFffF'",
                "text": "The bassist glanced at her and took out her phone. Her old friend of many years has long been accustomed to her indignation - an almost argumentative conversation is part of their communication."
            }
        ],
        "atts": {
            "dialog": [
                {
                    "font": "en-dia",
                    "fontSize": 34
                },
                {
                    "font": {},
                    "fontSize": {}
                }
            ]
        }
    },
    "33": {
        "speaker": "Soyo Nagasaki",
        "spans": [
            {
                "html": "style='color:#FfFffF'",
                "text": "Then I'll send a red Super Chat to cover it up."
            }
        ],
        "atts": {
            "dialog": [
                {
                    "font": "en-dia",
                    "fontSize": 34
                },
                {
                    "font": {},
                    "fontSize": {}
                }
            ]
        }
    },
    "34": {
        "speaker": "",
        "spans": [
            {
                "html": "style='color:#FfFffF'",
                "text": "Taki hurriedly grabbed her wrist, trying to stop this overbearing, nouveau riche behavior. Although she still forgets that her mouth can be used to speak when she is nervous, at least she won't grab her collar in a red-faced rage like she did in her adolescence."
            }
        ],
        "atts": {
            "dialog": [
                {
                    "font": "en-dia",
                    "fontSize": 34
                },
                {
                    "font": {},
                    "fontSize": {}
                }
            ]
        }
    },
    "35": {
        "speaker": "",
        "spans": [
            {
                "html": "style='color:#FfFffF'",
                "text": "Soyo Nagasaki obediently put down her phone, even though she didn't even turn it on."
            }
        ],
        "atts": {}
    },
    "36": {
        "speaker": "Soyo Nagasaki",
        "spans": [
            {
                "html": "style='color:#FfFffF'",
                "text": "Was little Taki's class today smooth? Are the students naughty? Were you late leaving in the morning?"
            }
        ],
        "atts": {
            "dialog": [
                {
                    "font": "en-dia",
                    "fontSize": 34
                },
                {
                    "font": {},
                    "fontSize": {}
                }
            ]
        }
    },
    "37": {
        "speaker": "Taki Shiina",
        "spans": [
            {
                "html": "style='color:#FfFffF'",
                "text": "...Huh?"
            }
        ],
        "atts": {}
    },
    "38": {
        "speaker": "Taki Shiina",
        "spans": [
            {
                "html": "style='color:#FfFffF'",
                "text": "Why did the topic suddenly come here?"
            }
        ],
        "atts": {}
    },
    "39": {
        "speaker": "Taki Shiina",
        "spans": [
            {
                "html": "style='color:#FfFffF'",
                "text": "It's all okay."
            }
        ],
        "atts": {}
    },
    "40": {
        "speaker": "Soyo Nagasaki",
        "spans": [
            {
                "html": "style='color:#FfFffF'",
                "text": "That's right. Little Taki is really amazing, she can handle any job well, and she is always on time."
            }
        ],
        "atts": {
            "dialog": [
                {
                    "font": "en-dia",
                    "fontSize": 34
                },
                {
                    "font": {},
                    "fontSize": {}
                }
            ]
        }
    },
    "41": {
        "speaker": "Soyo Nagasaki",
        "spans": [
            {
                "html": "style='color:#FfFffF'",
                "text": "Our company often deducts bonuses from newcomers for being late, and there are always people complaining in private that their wages are not enough to spend."
            }
        ],
        "atts": {
            "dialog": [
                {
                    "font": "en-dia",
                    "fontSize": 34
                },
                {
                    "font": {},
                    "fontSize": {}
                }
            ]
        }
    },
    "42": {
        "speaker": "Taki Shiina",
        "spans": [
            {
                "html": "style='color:#FfFffF'",
                "text": "What are you trying to say?"
            }
        ],
        "atts": {}
    },
    "43": {
        "speaker": "Soyo Nagasaki",
        "spans": [
            {
                "html": "style='color:#FfFffF'",
                "text": "So little Taki is going to pay to settle things?"
            }
        ],
        "atts": {
            "dialog": [
                {
                    "font": "en-dia",
                    "fontSize": 34
                },
                {
                    "font": {},
                    "fontSize": {}
                }
            ]
        }
    },
    "44": {
        "speaker": "",
        "spans": [
            {
                "html": "style='color:#FfFffF'",
                "text": "Twisting and turning. The troublesome person and her troublesome way of speaking. Hunters who have maxed out their social skills always like to lure people into a trap. Taki Shiina always falls into the trap again and again."
            }
        ],
        "atts": {
            "dialog": [
                {
                    "font": "en-dia",
                    "fontSize": 34
                },
                {
                    "font": {},
                    "fontSize": {}
                }
            ]
        }
    },
    "45": {
        "speaker": "",
        "spans": [
            {
                "html": "style='color:#FfFffF'",
                "text": "But unfortunately, this time it was letting a wolf into the house."
            }
        ],
        "atts": {
            "dialog": [
                {
                    "font": "en-dia",
                    "fontSize": 34
                },
                {
                    "font": {},
                    "fontSize": {}
                }
            ]
        }
    },
    "46": {
        "speaker": "",
        "spans": [
            {
                "html": "style='color:#FfFffF'",
                "text": "Taki Shiina, who had been dizzy for a long time, finally became confident and justified."
            }
        ],
        "atts": {
            "dialog": [
                {
                    "font": "en-dia",
                    "fontSize": 34
                },
                {
                    "font": {},
                    "fontSize": {}
                }
            ]
        }
    },
    "47": {
        "speaker": "Taki Shiina",
        "spans": [
            {
                "html": "style='color:#FfFffF'",
                "text": "I didn't say I wanted to leave a message, just block or report them."
            }
        ],
        "atts": {}
    },
    "48": {
        "speaker": "Taki Shiina",
        "spans": [
            {
                "html": "style='color:#FfFffF'",
                "text": "Although I can't stand it, I don't plan to always use money to solve it. After all, it's impossible for me to stare at every live stream. The situation is not that serious, Anon can handle it herself."
            }
        ],
        "atts": {}
    },
    "49": {
        "speaker": "Taki Shiina",
        "spans": [
            {
                "html": "style='color:#FfFffF'",
                "text": "We are not her parents, why interfere in everything, don't spoil her too much."
            }
        ],
        "atts": {}
    },
    "50": {
        "speaker": "",
        "spans": [
            {
                "html": "style='color:#FfFffF'",
                "text": "The hunter who missed her target clenched her sleeves."
            }
        ],
        "atts": {
            "dialog": [
                {
                    "font": "en-dia",
                    "fontSize": 34
                },
                {
                    "font": {},
                    "fontSize": {}
                }
            ]
        }
    },
    "51": {
        "speaker": "Soyo Nagasaki",
        "spans": [
            {
                "html": "style='color:#FfFffF'",
                "text": "It's getting dark, and it's not good to be parked downstairs for too long. Let's go."
            }
        ],
        "atts": {
            "dialog": [
                {
                    "font": "en-dia",
                    "fontSize": 34
                },
                {
                    "font": {},
                    "fontSize": {}
                }
            ]
        }
    },
    "52": {
        "speaker": "Taki Shiina",
        "spans": [
            {
                "html": "style='color:#FfFffF'",
                "text": "It was already dark when we came, right?"
            }
        ],
        "atts": {}
    },
    "53": {
        "speaker": "",
        "spans": [
            {
                "html": "style='color:#FfFffF'",
                "text": "The kind-hearted drummer complained in her heart, but finally did not press her advantage. For people who are both sensitive and thin-skinned, you can't corner them too much."
            }
        ],
        "atts": {
            "dialog": [
                {
                    "font": "en-dia",
                    "fontSize": 34
                },
                {
                    "font": {},
                    "fontSize": {}
                }
            ]
        }
    },
    "54": {
        "speaker": "",
        "spans": [
            {
                "html": "style='color:#FfFffF'",
                "text": "So the driver naturally opened the back seat door first."
            }
        ],
        "atts": {
            "dialog": [
                {
                    "font": "en-dia",
                    "fontSize": 34
                },
                {
                    "font": {},
                    "fontSize": {}
                }
            ]
        }
    },
    "55": {
        "speaker": "",
        "spans": [
            {
                "html": "style='color:#FfFffF'",
                "text": "The car started smoothly, without her familiar rumble, and she didn't have to sit in place waiting for the engine to warm up."
            }
        ],
        "atts": {
            "dialog": [
                {
                    "font": "en-dia",
                    "fontSize": 34
                },
                {
                    "font": {},
                    "fontSize": {}
                }
            ]
        }
    },
    "56": {
        "speaker": "",
        "spans": [
            {
                "html": "style='color:#FfFffF'",
                "text": "The road was wide, and the driver didn't need to be nervous and focused, and she didn't need to stick her head out to confirm how far the wall was from the rearview mirror. She just had to drive."
            }
        ],
        "atts": {
            "dialog": [
                {
                    "font": "en-dia",
                    "fontSize": 34
                },
                {
                    "font": {},
                    "fontSize": {}
                }
            ]
        }
    },
    "57": {
        "speaker": "",
        "spans": [
            {
                "html": "style='color:#FfFffF'",
                "text": "The car music hadn't started yet, and the safe driver took off her headphones, away from the electronic harassment of the YouTube streamer, and the world was quiet."
            }
        ],
        "atts": {
            "dialog": [
                {
                    "font": "en-dia",
                    "fontSize": 34
                },
                {
                    "font": {},
                    "fontSize": {}
                }
            ]
        }
    },
    "58": {
        "speaker": "Soyo Nagasaki",
        "spans": [
            {
                "html": "style='color:#FfFffF'",
                "text": "Little Tomori also spoils little Anon, and you always indulge little Tomori."
            }
        ],
        "atts": {
            "dialog": [
                {
                    "font": "en-dia",
                    "fontSize": 34
                },
                {
                    "font": {},
                    "fontSize": {}
                }
            ]
        }
    },
    "59": {
        "speaker": "",
        "spans": [
            {
                "html": "style='color:#FfFffF'",
                "text": "The driver drove into the twilight, without looking sideways."
            }
        ],
        "atts": {
            "dialog": [
                {
                    "font": "en-dia",
                    "fontSize": 34
                },
                {
                    "font": {},
                    "fontSize": {}
                }
            ]
        }
    },
    "60": {
        "speaker": "",
        "spans": [
            {
                "html": "style='color:#FfFffF'",
                "text": "The passenger in the back seat didn't have any extra words after firing a cold shot. The car audio took over the conversation and filled the silent space."
            }
        ],
        "atts": {
            "dialog": [
                {
                    "font": "en-dia",
                    "fontSize": 34
                },
                {
                    "font": {},
                    "fontSize": {}
                }
            ]
        }
    },
    "61": {
        "speaker": "",
        "spans": [
            {
                "html": "style='color:#FfFffF'",
                "text": "Just as she was driving out of the community entrance, Taki was still thinking about whether she should take responsibility for the communication; however, once she merged into the rush hour traffic, she couldn't spare that much thought."
            }
        ],
        "atts": {
            "dialog": [
                {
                    "font": "en-dia",
                    "fontSize": 34
                },
                {
                    "font": {},
                    "fontSize": {}
                }
            ]
        }
    },
    "62": {
        "speaker": "",
        "spans": [
            {
                "html": "style='color:#FfFffF'",
                "text": "The red light, which seemed to be getting longer and longer in front of the long line of cars, lit up. The driver slowly reduced her speed, trying not to wake the lady who was taking a nap in the back seat."
            }
        ],
        "atts": {
            "dialog": [
                {
                    "font": "en-dia",
                    "fontSize": 34
                },
                {
                    "font": {},
                    "fontSize": {}
                }
            ]
        }
    },
    "63": {
        "speaker": "Soyo Nagasaki",
        "spans": [
            {
                "html": "style='color:#FfFffF'",
                "text": "Where are we?"
            }
        ],
        "atts": {
            "dialog": [
                {
                    "font": "en-dia",
                    "fontSize": 34
                },
                {
                    "font": {},
                    "fontSize": {}
                }
            ]
        }
    },
    "64": {
        "speaker": "",
        "spans": [
            {
                "html": "style='color:#FfFffF'",
                "text": "Ineffective effort."
            }
        ],
        "atts": {
            "dialog": [
                {
                    "font": "en-dia",
                    "fontSize": 34
                },
                {
                    "font": {},
                    "fontSize": {}
                }
            ]
        }
    },
    "65": {
        "speaker": "Taki Shiina",
        "spans": [
            {
                "html": "style='color:#FfFffF'",
                "text": "Are you awake?"
            }
        ],
        "atts": {}
    },
    "66": {
        "speaker": "Soyo Nagasaki",
        "spans": [
            {
                "html": "style='color:#FfFffF'",
                "text": "...Not asleep."
            }
        ],
        "atts": {
            "dialog": [
                {
                    "font": "en-dia",
                    "fontSize": 34
                },
                {
                    "font": {},
                    "fontSize": {}
                }
            ]
        }
    },
    "67": {
        "speaker": "Soyo Nagasaki",
        "spans": [
            {
                "html": "style='color:#FfFffF'",
                "text": "Where to?"
            }
        ],
        "atts": {
            "dialog": [
                {
                    "font": "en-dia",
                    "fontSize": 34
                },
                {
                    "font": {},
                    "fontSize": {}
                }
            ]
        }
    },
    "68": {
        "speaker": "Taki Shiina",
        "spans": [
            {
                "html": "style='color:#FfFffF'",
                "text": "Your house."
            }
        ],
        "atts": {}
    },
    "69": {
        "speaker": "Taki Shiina",
        "spans": [
            {
                "html": "style='color:#FfFffF'",
                "text": "(Don't you have an appointment with me? Of course we're going to your place.)"
            }
        ],
        "atts": {}
    },
    "70": {
        "speaker": "Soyo Nagasaki",
        "spans": [
            {
                "html": "style='color:#FfFffF'",
                "text": "Then how will you get back?"
            }
        ],
        "atts": {
            "dialog": [
                {
                    "font": "en-dia",
                    "fontSize": 34
                },
                {
                    "font": {},
                    "fontSize": {}
                }
            ]
        }
    },
    "71": {
        "speaker": "Taki Shiina",
        "spans": [
            {
                "html": "style='color:#FfFffF'",
                "text": "(We won't be chatting for too long, right? It's impossible to miss the train. I can just go back myself.)"
            }
        ],
        "atts": {}
    },
    "72": {
        "speaker": "",
        "spans": [
            {
                "html": "style='color:#FfFffF'",
                "text": "Taki really wanted to say what she was thinking, but Soyo would never treat her work like this."
            }
        ],
        "atts": {
            "dialog": [
                {
                    "font": "en-dia",
                    "fontSize": 34
                },
                {
                    "font": {},
                    "fontSize": {}
                }
            ]
        }
    },
    "73": {
        "speaker": "",
        "spans": [
            {
                "html": "style='color:#FfFffF'",
                "text": "Even in band matters, when Soyo really needs to take over, this troublesome old friend will sigh and arrange the schedule clearly. Why isn't it like this when it comes to herself? Does the thinking capacity suddenly get cut off when the two of them are together?"
            }
        ],
        "atts": {
            "dialog": [
                {
                    "font": "en-dia",
                    "fontSize": 34
                },
                {
                    "font": {},
                    "fontSize": {}
                }
            ]
        }
    },
    "74": {
        "speaker": "",
        "spans": [
            {
                "html": "style='color:#FfFffF'",
                "text": "But during the red light, the driver raised her eyes and glanced at the passenger's expression in the car's rearview mirror, and chose to read the air."
            }
        ],
        "atts": {
            "dialog": [
                {
                    "font": "en-dia",
                    "fontSize": 34
                },
                {
                    "font": {},
                    "fontSize": {}
                }
            ]
        }
    },
    "75": {
        "speaker": "",
        "spans": [
            {
                "html": "style='color:#FfFffF'",
                "text": "She sighed, trying to soften her tone, so that what she was about to say didn't sound like a complaint, but a sincere suggestion."
            }
        ],
        "atts": {
            "dialog": [
                {
                    "font": "en-dia",
                    "fontSize": 34
                },
                {
                    "font": {},
                    "fontSize": {}
                }
            ]
        }
    },
    "76": {
        "speaker": "Taki Shiina",
        "spans": [
            {
                "html": "style='color:#FfFffF'",
                "text": "If you have any plans, tell me now."
            }
        ],
        "atts": {}
    },
    "77": {
        "speaker": "",
        "spans": [
            {
                "html": "style='color:#FfFffF'",
                "text": "The person leaning on the back seat closed her eyes again, avoiding the inclusive and familiar eye contact in the car's rearview mirror. Now is not the time to be on the Live stage."
            }
        ],
        "atts": {
            "dialog": [
                {
                    "font": "en-dia",
                    "fontSize": 34
                },
                {
                    "font": {},
                    "fontSize": {}
                }
            ]
        }
    },
    "78": {
        "speaker": "Soyo Nagasaki",
        "spans": [
            {
                "html": "style='color:#FfFffF'",
                "text": "Can you turn at the next intersection?"
            }
        ],
        "atts": {
            "dialog": [
                {
                    "font": "en-dia",
                    "fontSize": 34
                },
                {
                    "font": {},
                    "fontSize": {}
                }
            ]
        }
    }
}