{
    "0": {
        "speaker": "",
        "spans": [
            {
                "html": "style='color:#FfFffF'",
                "text": "When Taki rushed into the bedroom, the black cat's tail had just disappeared behind the curtain."
            }
        ],
        "atts": {
            "dialog": [
                {
                    "font": "en-dia",
                    "fontSize": 34
                },
                {
                    "font": {},
                    "fontSize": {}
                }
            ]
        }
    },
    "1": {
        "speaker": "",
        "spans": [
            {
                "html": "style='color:#FfFffF'",
                "text": "The owner of the bedroom, who silently followed in, just stared blankly behind her. The silence made Tomori feel as if she had returned to the few seconds of silence after a live performance, before the audience applauded and cheered."
            }
        ],
        "atts": {
            "dialog": [
                {
                    "font": "en-dia",
                    "fontSize": 34
                },
                {
                    "font": {},
                    "fontSize": {}
                }
            ]
        }
    },
    "2": {
        "speaker": "",
        "spans": [
            {
                "html": "style='color:#FfFffF'",
                "text": "The enormous sense of confusion was like an airbag that had exploded open, pushing her to get closer to Taki."
            }
        ],
        "atts": {
            "dialog": [
                {
                    "font": "en-dia",
                    "fontSize": 34
                },
                {
                    "font": {},
                    "fontSize": {}
                }
            ]
        }
    },
    "3": {
        "speaker": "",
        "spans": [
            {
                "html": "style='color:#FfFffF'",
                "text": "—But they were already standing so close that she could only look back in the direction Taki was looking—the swaying of the curtain gradually stopped."
            }
        ],
        "atts": {
            "dialog": [
                {
                    "font": "en-dia",
                    "fontSize": 34
                },
                {
                    "font": {},
                    "fontSize": {}
                }
            ]
        }
    },
    "4": {
        "speaker": "Tomori Takamatsu",
        "spans": [
            {
                "html": "style='color:#FfFffF'",
                "text": "Is there...something there?"
            }
        ],
        "atts": {
            "dialog": [
                {},
                {
                    "alpha": {}
                }
            ]
        }
    },
    "5": {
        "speaker": "",
        "spans": [
            {
                "html": "style='color:#FfFffF'",
                "text": "The black cat had completely disappeared behind the curtain, but the window was tightly closed, which meant it had nowhere to go. Just get closer, lift the curtain, and the black animal would be the best opening line."
            }
        ],
        "atts": {
            "dialog": [
                {
                    "font": "en-dia",
                    "fontSize": 34
                },
                {
                    "font": {},
                    "fontSize": {}
                }
            ]
        }
    },
    "6": {
        "speaker": "Taki Shiina",
        "spans": [
            {
                "html": "style='color:#FfFffF'",
                "text": "Tomori, it's behind the window."
            }
        ],
        "atts": {
            "dialog": [
                {},
                {
                    "alpha": {}
                }
            ]
        }
    },
    "7": {
        "speaker": "",
        "spans": [
            {
                "html": "style='color:#FfFffF'",
                "text": "So Taki Shiina walked over and pulled back the curtain. There was nothing on the windowsill."
            }
        ],
        "atts": {
            "dialog": [
                {
                    "font": "en-dia",
                    "fontSize": 34
                },
                {
                    "font": {},
                    "fontSize": {}
                }
            ]
        }
    },
    "8": {
        "speaker": "Taki Shiina",
        "spans": [
            {
                "html": "style='color:#FfFffF'",
                "text": "(As expected...)"
            }
        ],
        "atts": {
            "dialog": [
                {},
                {
                    "alpha": {}
                }
            ]
        }
    },
    "9": {
        "speaker": "",
        "spans": [
            {
                "html": "style='color:#FfFffF'",
                "text": "In the \"worst possible\" scenario list, Taki Shiina had already thought of this result, so she didn't show much surprise."
            }
        ],
        "atts": {
            "dialog": [
                {
                    "font": "en-dia",
                    "fontSize": 34
                },
                {
                    "font": {},
                    "fontSize": {}
                }
            ]
        }
    },
    "10": {
        "speaker": "",
        "spans": [
            {
                "html": "style='color:#FfFffF'",
                "text": "Although the black cat was not on the windowsill, the countdown was still in the window frame, so she continued."
            }
        ],
        "atts": {
            "dialog": [
                {
                    "font": "en-dia",
                    "fontSize": 34
                },
                {
                    "font": {},
                    "fontSize": {}
                }
            ]
        }
    },
    "11": {
        "speaker": "Taki Shiina",
        "spans": [
            {
                "html": "style='color:#FfFffF'",
                "text": "Can Tomori see it?"
            }
        ],
        "atts": {
            "dialog": [
                {},
                {
                    "alpha": {}
                }
            ]
        }
    },
    "12": {
        "speaker": "",
        "spans": [
            {
                "html": "style='color:#FfFffF'",
                "text": "Tomori shook her head, and unease wound up her eyebrows. The familiarity with this unease twisted the spring hard, and her eyebrows locked together."
            }
        ],
        "atts": {
            "dialog": [
                {
                    "font": "en-dia",
                    "fontSize": 34
                },
                {
                    "font": {},
                    "fontSize": {}
                }
            ]
        }
    },
    "13": {
        "speaker": "Taki Shiina",
        "spans": [
            {
                "html": "style='color:#FfFffF'",
                "text": "A few days ago, after a sudden fainting spell, a countdown timer appeared above my head."
            }
        ],
        "atts": {
            "dialog": [
                {},
                {
                    "alpha": {}
                }
            ]
        }
    },
    "14": {
        "speaker": "Taki Shiina",
        "spans": [
            {
                "html": "style='color:#FfFffF'",
                "text": "At the same time, my heart rate per minute has also been fixed at a multiple of ten, and it decreases by ten times after midnight every day."
            }
        ],
        "atts": {
            "dialog": [
                {},
                {
                    "alpha": {}
                }
            ]
        }
    },
    "15": {
        "speaker": "Taki Shiina",
        "spans": [
            {
                "html": "style='color:#FfFffF'",
                "text": "When the countdown reaches zero...my heartbeat should also stop."
            }
        ],
        "atts": {
            "dialog": [
                {},
                {
                    "alpha": {}
                }
            ]
        }
    },
    "16": {
        "speaker": "",
        "spans": [
            {
                "html": "style='color:#FfFffF'",
                "text": "Even the briefest silence seemed long at this moment. The unspoken words could not be clearer - what else can a heart that doesn't beat represent?"
            }
        ],
        "atts": {
            "dialog": [
                {
                    "font": "en-dia",
                    "fontSize": 34
                },
                {
                    "font": {},
                    "fontSize": {}
                }
            ]
        }
    },
    "17": {
        "speaker": "Tomori Takamatsu",
        "spans": [
            {
                "html": "style='color:#FfFffF'",
                "text": "Taki, you're not kidding, are you?"
            }
        ],
        "atts": {
            "dialog": [
                {},
                {
                    "alpha": {}
                }
            ]
        }
    },
    "18": {
        "speaker": "",
        "spans": [
            {
                "html": "style='color:#FfFffF'",
                "text": "Tomori's voice trembled slightly. She knew that the other person was not one to joke about such serious matters, and the heaviness on her face was not feigned."
            }
        ],
        "atts": {
            "dialog": [
                {
                    "font": "en-dia",
                    "fontSize": 34
                },
                {
                    "font": {},
                    "fontSize": {}
                }
            ]
        }
    },
    "19": {
        "speaker": "",
        "spans": [
            {
                "html": "style='color:#FfFffF'",
                "text": "But Tomori asked anyway, as if Taki would really affirm that \"she was kidding.\""
            }
        ],
        "atts": {
            "dialog": [
                {
                    "font": "en-dia",
                    "fontSize": 34
                },
                {
                    "font": {},
                    "fontSize": {}
                }
            ]
        }
    },
    "20": {
        "speaker": "",
        "spans": [
            {
                "html": "style='color:#FfFffF'",
                "text": "In the face of a sudden disaster, Tomori activated her emergency mode as quickly as possible—trying to grasp at any possibility, no matter how small."
            }
        ],
        "atts": {
            "dialog": [
                {
                    "font": "en-dia",
                    "fontSize": 34
                },
                {
                    "font": {},
                    "fontSize": {}
                }
            ]
        }
    },
    "21": {
        "speaker": "",
        "spans": [
            {
                "html": "style='color:#FfFffF'",
                "text": "Taki took Tomori's hand and placed it on her chest."
            }
        ],
        "atts": {
            "dialog": [
                {
                    "font": "en-dia",
                    "fontSize": 34
                },
                {
                    "font": {},
                    "fontSize": {}
                }
            ]
        }
    },
    "22": {
        "speaker": "",
        "spans": [
            {
                "html": "style='color:#FfFffF'",
                "text": "With a heartbeat of nearly once per second, it was impossible for the vocalist not to be able to distinguish this steady and bizarre rhythm."
            }
        ],
        "atts": {
            "dialog": [
                {
                    "font": "en-dia",
                    "fontSize": 34
                },
                {
                    "font": {},
                    "fontSize": {}
                }
            ]
        }
    },
    "23": {
        "speaker": "",
        "spans": [
            {
                "html": "style='color:#FfFffF'",
                "text": "With a heartbeat that sounded only once every few seconds, it was impossible for the vocalist not to be able to distinguish this steady and bizarre rhythm. It was already a miracle that the person in front of her could still move."
            }
        ],
        "atts": {
            "dialog": [
                {
                    "font": "en-dia",
                    "fontSize": 34
                },
                {
                    "font": {},
                    "fontSize": {}
                }
            ]
        }
    },
    "24": {
        "speaker": "Tomori Takamatsu",
        "spans": [
            {
                "html": "style='color:#FfFffF'",
                "text": "Why...?"
            }
        ],
        "atts": {
            "dialog": [
                {},
                {
                    "alpha": {}
                }
            ]
        }
    },
    "25": {
        "speaker": "Tomori Takamatsu",
        "spans": [
            {
                "html": "style='color:#FfFffF'",
                "text": "Does Taki have any idea?"
            }
        ],
        "atts": {
            "dialog": [
                {},
                {
                    "alpha": {}
                }
            ]
        }
    },
    "26": {
        "speaker": "Tomori Takamatsu",
        "spans": [
            {
                "html": "style='color:#FfFffF'",
                "text": "Could it be a curse? Has Taki tried looking for someone to exorcise it?"
            }
        ],
        "atts": {
            "dialog": [
                {},
                {
                    "alpha": {}
                }
            ]
        }
    },
    "27": {
        "speaker": "Tomori Takamatsu",
        "spans": [
            {
                "html": "style='color:#FfFffF'",
                "text": "Or is it just that you didn't sleep well? It might just be a hallucination caused by lack of sleep! Maybe it's just that you're too stressed about the new song..."
            }
        ],
        "atts": {
            "dialog": [
                {},
                {
                    "alpha": {}
                }
            ]
        }
    },
    "28": {
        "speaker": "",
        "spans": [
            {
                "html": "style='color:#FfFffF'",
                "text": "She kept throwing out questions, her tone becoming more and more rapid, but her head was drooping lower and lower."
            }
        ],
        "atts": {
            "dialog": [
                {
                    "font": "en-dia",
                    "fontSize": 34
                },
                {
                    "font": {},
                    "fontSize": {}
                }
            ]
        }
    },
    "29": {
        "speaker": "",
        "spans": [
            {
                "html": "style='color:#FfFffF'",
                "text": "It wasn't until the basket, from which almost all the ingredients had been taken, leaving only a large pile of energy jellies, entered her vision that she finally stopped."
            }
        ],
        "atts": {
            "dialog": [
                {
                    "font": "en-dia",
                    "fontSize": 34
                },
                {
                    "font": {},
                    "fontSize": {}
                }
            ]
        }
    },
    "30": {
        "speaker": "Tomori Takamatsu",
        "spans": [
            {
                "html": "style='color:#FfFffF'",
                "text": "Taki, you were actually stocking up on food for this reason, weren't you?"
            }
        ],
        "atts": {
            "dialog": [
                {},
                {
                    "alpha": {}
                }
            ]
        }
    },
    "31": {
        "speaker": "Tomori Takamatsu",
        "spans": [
            {
                "html": "style='color:#FfFffF'",
                "text": "Taki, you didn't buy so many vegetables to practice cooking, did you?"
            }
        ],
        "atts": {
            "dialog": [
                {},
                {
                    "alpha": {}
                }
            ]
        }
    },
    "32": {
        "speaker": "Taki Shiina",
        "spans": [
            {
                "html": "style='color:#FfFffF'",
                "text": "......"
            }
        ],
        "atts": {
            "dialog": [
                {},
                {
                    "alpha": {}
                }
            ]
        }
    },
    "33": {
        "speaker": "",
        "spans": [
            {
                "html": "style='color:#FfFffF'",
                "text": "Tomori took a step back. The tightly furrowed brows loosened because she had found some kind of answer, smoothing out like the breath that was suspended in Taki Shiina's throat, afraid to exhale."
            }
        ],
        "atts": {
            "dialog": [
                {
                    "font": "en-dia",
                    "fontSize": 34
                },
                {
                    "font": {},
                    "fontSize": {}
                }
            ]
        }
    },
    "34": {
        "speaker": "Tomori Takamatsu",
        "spans": [
            {
                "html": "style='color:#FfFffF'",
                "text": "Taki...is it because you've already made up your mind to write the song before then?"
            }
        ],
        "atts": {
            "dialog": [
                {},
                {
                    "alpha": {}
                }
            ]
        }
    },
    "35": {
        "speaker": "Taki Shiina",
        "spans": [
            {
                "html": "style='color:#FfFffF'",
                "text": "......"
            }
        ],
        "atts": {
            "dialog": [
                {},
                {
                    "alpha": {}
                }
            ]
        }
    },
    "36": {
        "speaker": "",
        "spans": [
            {
                "html": "style='color:#FfFffF'",
                "text": "I can't say it. Even if I have such a plan, it is only a plan at the moment. The progress of the song is sometimes fast and sometimes slow, and it is difficult to guarantee whether it can be handed in before the deadline."
            }
        ],
        "atts": {
            "dialog": [
                {
                    "font": "en-dia",
                    "fontSize": 34
                },
                {
                    "font": {},
                    "fontSize": {}
                }
            ]
        }
    },
    "37": {
        "speaker": "",
        "spans": [
            {
                "html": "style='color:#FfFffF'",
                "text": "If only I could master it a little more, if only there was a little more time - although I have lamented this countless times, right now, the song can only be completed if I start working on it, because, because."
            }
        ],
        "atts": {
            "dialog": [
                {
                    "font": "en-dia",
                    "fontSize": 34
                },
                {
                    "font": {},
                    "fontSize": {}
                }
            ]
        }
    },
    "38": {
        "speaker": "Taki Shiina",
        "spans": [
            {
                "html": "style='color:#FfFffF'",
                "text": "I want to leave something behind."
            }
        ],
        "atts": {
            "dialog": [
                {},
                {
                    "alpha": {}
                }
            ]
        }
    },
    "39": {
        "speaker": "Tomori Takamatsu",
        "spans": [
            {
                "html": "style='color:#FfFffF'",
                "text": "Why, why can't you put yourself first?"
            }
        ],
        "atts": {
            "dialog": [
                {},
                {
                    "alpha": {}
                }
            ]
        }
    },
    "40": {
        "speaker": "Tomori Takamatsu",
        "spans": [
            {
                "html": "style='color:#FfFffF'",
                "text": "If something like suddenly fainting doesn't happen... how long is Taki going to hide it?"
            }
        ],
        "atts": {
            "dialog": [
                {},
                {
                    "alpha": {}
                }
            ]
        }
    },
    "41": {
        "speaker": "Tomori Takamatsu",
        "spans": [
            {
                "html": "style='color:#FfFffF'",
                "text": "I don't like... Taki like this."
            }
        ],
        "atts": {
            "dialog": [
                {},
                {
                    "alpha": {}
                }
            ]
        }
    },
    "42": {
        "speaker": "",
        "spans": [
            {
                "html": "style='color:#FfFffF'",
                "text": "Organizing words became a laborious task. Taki Shiina now needed to vibrate her vocal cords, open her mouth, and say something to salvage the situation, but she fell at the first step—organizing a thought."
            }
        ],
        "atts": {
            "dialog": [
                {
                    "font": "en-dia",
                    "fontSize": 34
                },
                {
                    "font": {},
                    "fontSize": {}
                }
            ]
        }
    },
    "43": {
        "speaker": "",
        "spans": [
            {
                "html": "style='color:#FfFffF'",
                "text": "The waves of emotion knocked her to the ground, her lungs began to gasp in rhythm with the tide, and tears began to be produced from the corners of her eyes because of the sourness. She had experienced similar feelings many times because of Tomori's lyrics, and this was the one she hated the most."
            }
        ],
        "atts": {
            "dialog": [
                {
                    "font": "en-dia",
                    "fontSize": 34
                },
                {
                    "font": {},
                    "fontSize": {}
                }
            ]
        }
    },
    "44": {
        "speaker": "",
        "spans": [
            {
                "html": "style='color:#FfFffF'",
                "text": "Tomori seemed to have exhausted all her strength as well, squatting down and curling up into a small ball, her shoulders twitching slightly. The sound came through the overlapping coat and arms, sounding more muffled than usual."
            }
        ],
        "atts": {
            "dialog": [
                {
                    "font": "en-dia",
                    "fontSize": 34
                },
                {
                    "font": {},
                    "fontSize": {}
                }
            ]
        }
    },
    "45": {
        "speaker": "Tomori Takamatsu",
        "spans": [
            {
                "html": "style='color:#FfFffF'",
                "text": "Was that the reason during rehearsal that day as well? How long will the countdown last?"
            }
        ],
        "atts": {
            "dialog": [
                {},
                {
                    "alpha": {}
                }
            ]
        }
    },
    "46": {
        "speaker": "Taki Shiina",
        "spans": [
            {
                "html": "style='color:#FfFffF'",
                "text": "Tomori..."
            }
        ],
        "atts": {
            "dialog": [
                {},
                {
                    "alpha": {}
                }
            ]
        }
    },
    "47": {
        "speaker": "",
        "spans": [
            {
                "html": "style='color:#FfFffF'",
                "text": "She wanted to run away again."
            }
        ],
        "atts": {
            "dialog": [
                {
                    "font": "en-dia",
                    "fontSize": 34
                },
                {
                    "font": {},
                    "fontSize": {}
                }
            ]
        }
    },
    "48": {
        "speaker": "",
        "spans": [
            {
                "html": "style='color:#FfFffF'",
                "text": "Tomori, squatting on the ground and sobbing, was fragile and vulnerable, but Tomori, who wanted to grab the person next to her, was tenacious and powerful. She had only seen this contradictory combination in Rupert's Tears, and that itself was not something that should exist in nature, so it was normal to feel strange and want to retreat."
            }
        ],
        "atts": {
            "dialog": [
                {
                    "font": "en-dia",
                    "fontSize": 34
                },
                {
                    "font": {},
                    "fontSize": {}
                }
            ]
        }
    },
    "49": {
        "speaker": "",
        "spans": [
            {
                "html": "style='color:#FfFffF'",
                "text": "Just tell a little lie and push the date of death back a day. Even a domestic dog knows to hide secretly when its life is coming to an end so that people don't find out. As a human with more abundant emotions, there is even less reason to let Tomori watch her leave with her own eyes."
            }
        ],
        "atts": {
            "dialog": [
                {
                    "font": "en-dia",
                    "fontSize": 34
                },
                {
                    "font": {},
                    "fontSize": {}
                }
            ]
        }
    },
    "50": {
        "speaker": "",
        "spans": [
            {
                "html": "style='color:#FfFffF'",
                "text": "Perhaps she would have already lost consciousness by the time Tomori arrived, and a prepared surprise could effectively dissipate the sorrow of parting. Perhaps there would also be resentment towards the lie, but it wouldn't be able to catch up with her who had already crossed the River Styx."
            }
        ],
        "atts": {
            "dialog": [
                {
                    "font": "en-dia",
                    "fontSize": 34
                },
                {
                    "font": {},
                    "fontSize": {}
                }
            ]
        }
    },
    "51": {
        "speaker": "Taki Shiina",
        "spans": [
            {
                "html": "style='color:#FfFffF'",
                "text": "[@v100] days left..."
            }
        ],
        "atts": {
            "dialog": [
                {},
                {
                    "alpha": {}
                }
            ]
        }
    },
    "52": {
        "speaker": "",
        "spans": [
            {
                "html": "style='color:#FfFffF'",
                "text": "She ultimately did not say the long-brewing lie. One mistake cannot be made again. The resentment of the lie could not catch up with her at that time, but the words of explanation could not escape the River Styx either, and could not reach Tomori's side."
            }
        ],
        "atts": {
            "dialog": [
                {
                    "font": "en-dia",
                    "fontSize": 34
                },
                {
                    "font": {},
                    "fontSize": {}
                }
            ]
        }
    },
    "53": {
        "speaker": "",
        "spans": [
            {
                "html": "style='color:#FfFffF'",
                "text": "Tomori took a deep breath, stood up, and took another step back. The sad tremor in her tone had disappeared, replaced by an action of hugging her arms, as if it were cold all around."
            }
        ],
        "atts": {
            "dialog": [
                {
                    "font": "en-dia",
                    "fontSize": 34
                },
                {
                    "font": {},
                    "fontSize": {}
                }
            ]
        }
    },
    "54": {
        "speaker": "Tomori Takamatsu",
        "spans": [
            {
                "html": "style='color:#FfFffF'",
                "text": "I'm sorry, Taki."
            }
        ],
        "atts": {
            "dialog": [
                {},
                {
                    "alpha": {}
                }
            ]
        }
    },
    "55": {
        "speaker": "Taki Shiina",
        "spans": [
            {
                "html": "style='color:#FfFffF'",
                "text": "(I should have closed the window...)"
            }
        ],
        "atts": {
            "dialog": [
                {},
                {
                    "alpha": {}
                }
            ]
        }
    },
    "56": {
        "speaker": "",
        "spans": [
            {
                "html": "style='color:#FfFffF'",
                "text": "Taki Shiina looked at Tomori Takamatsu, who was slowly walking backwards and finally leaning against the wall, and belatedly realized that this was a common defensive posture in psychology."
            }
        ],
        "atts": {
            "dialog": [
                {
                    "font": "en-dia",
                    "fontSize": 34
                },
                {
                    "font": {},
                    "fontSize": {}
                }
            ]
        }
    },
    "57": {
        "speaker": "Tomori Takamatsu",
        "spans": [
            {
                "html": "style='color:#FfFffF'",
                "text": "Do you remember when we said we'd form a band for life? Taki was the first to agree with me at the time."
            }
        ],
        "atts": {
            "dialog": [
                {},
                {
                    "alpha": {}
                }
            ]
        }
    },
    "58": {
        "speaker": "Tomori Takamatsu",
        "spans": [
            {
                "html": "style='color:#FfFffF'",
                "text": "No take-backs. A lifetime is a lifetime. Until your heart stops beating, Taki will still be our drummer and composer."
            }
        ],
        "atts": {
            "dialog": [
                {},
                {
                    "alpha": {}
                }
            ]
        }
    },
    "59": {
        "speaker": "Tomori Takamatsu",
        "spans": [
            {
                "html": "style='color:#FfFffF'",
                "text": "I'll give you the lyrics after that day. If Taki wants to pursue perfection, it's impossible to imagine the song you write in the end without lyrics, right?"
            }
        ],
        "atts": {
            "dialog": [
                {},
                {
                    "alpha": {}
                }
            ]
        }
    },
    "60": {
        "speaker": "Tomori Takamatsu",
        "spans": [
            {
                "html": "style='color:#FfFffF'",
                "text": "So Taki has to live well. I know this is a bit presumptuous, but Taki has to live until she waits for my lyrics."
            }
        ],
        "atts": {
            "dialog": [
                {},
                {
                    "alpha": {}
                }
            ]
        }
    },
    "61": {
        "speaker": "Tomori Takamatsu",
        "spans": [
            {
                "html": "style='color:#FfFffF'",
                "text": "Before that..."
            }
        ],
        "atts": {
            "dialog": [
                {},
                {
                    "alpha": {}
                }
            ]
        }
    },
    "62": {
        "speaker": "Tomori Takamatsu",
        "spans": [
            {
                "html": "style='color:#FfFffF'",
                "text": "For now, I don't want to see Taki."
            }
        ],
        "atts": {
            "dialog": [
                {},
                {
                    "alpha": {}
                }
            ]
        }
    },
    "63": {
        "speaker": "",
        "spans": [
            {
                "html": "style='color:#FfFffF'",
                "text": "When Tomori closed the door, a gust of wind was stirred up. When the chill of early spring hit Rikki's face, it brought a sense of dizziness. She closed her eyes and remembered that damage to the cochlear nerve could cause similar balance disorders, but why could she hear everything more clearly than usual now—"
            }
        ],
        "atts": {
            "dialog": [
                {
                    "font": "en-dia",
                    "fontSize": 34
                },
                {
                    "font": {},
                    "fontSize": {}
                }
            ]
        }
    },
    "64": {
        "speaker": "",
        "spans": [
            {
                "html": "style='color:#FfFffF'",
                "text": "She heard the rustling sound of fur rubbing against the window frame, the whistling sound of the wind blowing in from the window, the pattering sound of cat claws falling from a high place into a puddle and jumping away in a few steps."
            }
        ],
        "atts": {
            "dialog": [
                {
                    "font": "en-dia",
                    "fontSize": 34
                },
                {
                    "font": {},
                    "fontSize": {}
                }
            ]
        }
    },
    "65": {
        "speaker": "",
        "spans": [
            {
                "html": "style='color:#FfFffF'",
                "text": "She heard the plastic sound of the jelly packaging rubbing when the basket was picked up, the soft and slow footsteps of leather boots, and the gentle closing of the door page beside her."
            }
        ],
        "atts": {
            "dialog": [
                {
                    "font": "en-dia",
                    "fontSize": 34
                },
                {
                    "font": {},
                    "fontSize": {}
                }
            ]
        }
    },
    "66": {
        "speaker": "",
        "spans": [
            {
                "html": "style='color:#FfFffF'",
                "text": "She heard the dull thud of Tomori's entire body falling on the bed, and the crisp stretching sound before the quilt was lifted up and randomly crumpled into a ball."
            }
        ],
        "atts": {
            "dialog": [
                {
                    "font": "en-dia",
                    "fontSize": 34
                },
                {
                    "font": {},
                    "fontSize": {}
                }
            ]
        }
    },
    "67": {
        "speaker": "",
        "spans": [
            {
                "html": "style='color:#FfFffF'",
                "text": "She heard herself sighing deeply."
            }
        ],
        "atts": {
            "dialog": [
                {
                    "font": "en-dia",
                    "fontSize": 34
                },
                {
                    "font": {},
                    "fontSize": {}
                }
            ]
        }
    },
    "68": {
        "speaker": "Taki Shiina",
        "spans": [
            {
                "html": "style='color:#FfFffF'",
                "text": "What have I done..."
            }
        ],
        "atts": {
            "dialog": [
                {},
                {
                    "alpha": {}
                }
            ]
        }
    }
}