{
    "0": {
        "speaker": "",
        "spans": [
            {
                "html": "style='color:#FfFffF'",
                "text": "………"
            }
        ],
        "atts": []
    },
    "1": {
        "speaker": "",
        "spans": [
            {
                "html": "style='color:#FfFffF'",
                "text": "……"
            }
        ],
        "atts": []
    },
    "2": {
        "speaker": "Taki Shiina",
        "spans": [
            {
                "html": "style='color:#FfFffF'",
                "text": "Hmm… hmm…"
            }
        ],
        "atts": []
    },
    "3": {
        "speaker": "Taki Shiina",
        "spans": [
            {
                "html": "style='color:#FfFffF'",
                "text": "Hmm…"
            }
        ],
        "atts": []
    },
    "4": {
        "speaker": "",
        "spans": [
            {
                "html": "style='color:#FfFffF'",
                "text": "Her body remained weak. She moved slightly, feeling a sticky sensation—seems she had been sweating heavily."
            }
        ],
        "atts": []
    },
    "5": {
        "speaker": "",
        "spans": [
            {
                "html": "style='color:#FfFffF'",
                "text": "But the pain had truly subsided."
            }
        ],
        "atts": []
    },
    "6": {
        "speaker": "Taki Shiina",
        "spans": [
            {
                "html": "style='color:#FfFffF'",
                "text": "……"
            }
        ],
        "atts": []
    },
    "7": {
        "speaker": "Taki Shiina",
        "spans": [
            {
                "html": "style='color:#FfFffF'",
                "text": "(How long have I been asleep…?)"
            }
        ],
        "atts": []
    },
    "8": {
        "speaker": "",
        "spans": [
            {
                "html": "style='color:#FfFffF'",
                "text": "She propped herself up, every joint in her body crying out in pain."
            }
        ],
        "atts": []
    },
    "9": {
        "speaker": "",
        "spans": [
            {
                "html": "style='color:#FfFffF'",
                "text": "On the dining table, the digital clock showed it was almost 8 o'clock."
            }
        ],
        "atts": []
    },
    "10": {
        "speaker": "",
        "spans": [
            {
                "html": "style='color:#FfFffF'",
                "text": "—8 o'clock in 24-hour format."
            }
        ],
        "atts": []
    },
    "11": {
        "speaker": "Taki Shiina",
        "spans": [
            {
                "html": "style='color:#FfFffF'",
                "text": "(I slept… almost an entire day?!)"
            }
        ],
        "atts": []
    },
    "12": {
        "speaker": "",
        "spans": [
            {
                "html": "style='color:#FfFffF'",
                "text": "Taki lit up her phone’s screen, and the date confirmed the fact."
            }
        ],
        "atts": []
    },
    "13": {
        "speaker": "Taki Shiina",
        "spans": [
            {
                "html": "style='color:#FfFffF'",
                "text": "(All that time… wasted…)"
            }
        ],
        "atts": []
    },
    "14": {
        "speaker": "",
        "spans": [
            {
                "html": "style='color:#FfFffF'",
                "text": "The world outside was dark, and it seemed to be pouring with rain, though oddly there was no sound."
            }
        ],
        "atts": []
    },
    "15": {
        "speaker": "",
        "spans": [
            {
                "html": "style='color:#FfFffF'",
                "text": "Remaining in this position, Taki's mood sank to rock bottom."
            }
        ],
        "atts": []
    },
    "16": {
        "speaker": "",
        "spans": [
            {
                "html": "style='color:#FfFffF'",
                "text": "However, the chill in front of her nose quickly snapped her out of it. A few droplets on the floor appeared, glaringly red."
            }
        ],
        "atts": []
    },
    "17": {
        "speaker": "Taki Shiina",
        "spans": [
            {
                "html": "style='color:#FfFffF'",
                "text": "!!!"
            }
        ],
        "atts": []
    },
    "18": {
        "speaker": "",
        "spans": [
            {
                "html": "style='color:#FfFffF'",
                "text": "Taki scrambled to her feet, clutching her nose as she rushed into the bathroom."
            }
        ],
        "atts": []
    },
    "19": {
        "speaker": "",
        "spans": [
            {
                "html": "style='color:#FfFffF'",
                "text": "The faucet was turned to its limit, and icy cold water splashed onto her face, draining her warmth."
            }
        ],
        "atts": []
    },
    "20": {
        "speaker": "",
        "spans": [
            {
                "html": "style='color:#FfFffF'",
                "text": "Diluted streams of blood spread in the water like silk, spiraling into a pitch-black drain."
            }
        ],
        "atts": []
    },
    "21": {
        "speaker": "Taki Shiina",
        "spans": [
            {
                "html": "style='color:#FfFffF'",
                "text": "…Hah."
            }
        ],
        "atts": []
    },
    "22": {
        "speaker": "",
        "spans": [
            {
                "html": "style='color:#FfFffF'",
                "text": "A profound feeling of powerlessness gripped her."
            }
        ],
        "atts": []
    },
    "23": {
        "speaker": "Taki Shiina",
        "spans": [
            {
                "html": "style='color:#FfFffF'",
                "text": "(No time… I don’t have time to waste sleeping or feeling sick…)"
            }
        ],
        "atts": []
    },
    "24": {
        "speaker": "Taki Shiina",
        "spans": [
            {
                "html": "style='color:#FfFffF'",
                "text": "(…No time left… but why?)"
            }
        ],
        "atts": []
    },
    "25": {
        "speaker": "",
        "spans": [
            {
                "html": "style='color:#FfFffF'",
                "text": "For some inexplicable reason, she felt an overpowering urgency, as if being chased or standing on the brink of falling. It left her extremely restless and anxious."
            }
        ],
        "atts": []
    },
    "26": {
        "speaker": "Taki Shiina",
        "spans": [
            {
                "html": "style='color:#FfFffF'",
                "text": "(I feel like… I just dreamed of something… What was it…?)"
            }
        ],
        "atts": []
    },
    "27": {
        "speaker": "",
        "spans": [
            {
                "html": "style='color:#FfFffF'",
                "text": "Taki tried hard to recall her memories from when she fainted."
            }
        ],
        "atts": []
    },
    "28": {
        "speaker": "Taki Shiina",
        "spans": [
            {
                "html": "style='color:#FfFffF'",
                "text": "(I was so close… What was it… Something about time…)"
            }
        ],
        "atts": []
    },
    "29": {
        "speaker": "",
        "spans": [
            {
                "html": "style='color:#ff0000'",
                "text": "Time is running out."
            }
        ],
        "atts": {
            "dialog": [
                {
                    "fontSize": 48
                },
                {
                    "fontSize": {}
                }
            ]
        }
    },
    "30": {
        "speaker": "",
        "spans": [
            {
                "html": "style='color:#ffffff'",
                "text": "In that instant, she remembered."
            }
        ],
        "atts": []
    },
    "31": {
        "speaker": "",
        "spans": [
            {
                "html": "style='color:#FfFffF'",
                "text": "She abruptly raised her head."
            }
        ],
        "atts": []
    },
    "32": {
        "speaker": "",
        "spans": [
            {
                "html": "style='color:#FfFffF'",
                "text": "The bathroom mirror, long unused, was covered in a layer of dust and buildup. Through the haze, Taki thought she saw writing etched on the surface."
            }
        ],
        "atts": []
    },
    "33": {
        "speaker": "",
        "spans": [
            {
                "html": "style='color:#FfFffF'",
                "text": "She scooped up water with her hands and splashed it onto the mirror, then hurriedly wiped at it. The mirror squealed with an unpleasant sound."
            }
        ],
        "atts": []
    },
    "34": {
        "speaker": "",
        "spans": [
            {
                "html": "style='color:#FfFffF'",
                "text": "And then, she saw it—"
            }
        ],
        "atts": []
    },
    "35": {
        "speaker": "",
        "spans": [
            {
                "html": "style='color:#FfFffF'",
                "text": "Taki lunged forward and let out a gasp."
            }
        ],
        "atts": []
    },
    "36": {
        "speaker": "",
        "spans": [
            {
                "html": "style='color:#FfFffF'",
                "text": "Narration"
            }
        ],
        "atts": {
            "dialog": [
                {
                    "alpha": 0,
                    "fontSize": 30,
                    "height": 34,
                    "shadowEnabled": false,
                    "strokeColor": "#d57fdf",
                    "width": 413,
                    "x": 1284,
                    "y": 1102
                },
                {
                    "alpha": {},
                    "fontSize": {},
                    "height": {},
                    "shadowEnabled": {},
                    "strokeColor": {},
                    "width": {},
                    "x": {},
                    "y": {}
                }
            ],
            "nameBox": [
                {
                    "height": 156,
                    "x": -240,
                    "y": 586
                },
                {
                    "height": {},
                    "x": {},
                    "y": {}
                }
            ],
            "skipBox": [
                {
                    "alpha": 0,
                    "x": 1546,
                    "y": 1074
                },
                {
                    "alpha": {},
                    "x": {},
                    "y": {}
                }
            ]
        }
    }
}